{"Name": "Succession", "Version": "1.4.6", "Section": "Utilities", "Package": "git.shin.successionrestore", "Author": "Samg_is_a_Ninja", "Depends": "firmware-sbin, rsync", "Descript": "Restore without updating via rootfilesystem DMG. Fix all error in iOS 10.0.0 (32bit) -> iOS 13", "Arch": "iphoneos-arm", "Size": "1321302", "Time": "1581818074000"}
{"Name": "Succession", "Version": "1.4.11", "Section": "Utilities", "Package": "git.shin.successionrestore", "Author": "Samg_is_a_Ninja <samgisaninja@unc0ver.dev>", "Depends": "firmware-sbin, rsync", "Descript": "Restore without updating via rootfilesystem DMG", "Arch": "iphoneos-arm", "Size": "1326082", "Time": "1582941807000"}
